asyncproxybroker/__init__.py
asyncproxybroker/async_proxy_broker.py
asyncproxybroker/providers.py
asyncproxybroker-0.0.2.dist-info/METADATA
asyncproxybroker-0.0.2.dist-info/WHEEL
asyncproxybroker-0.0.2.dist-info/top_level.txt
asyncproxybroker-0.0.2.dist-info/RECORD
