Metadata-Version: 2.1
Name: asyncproxybroker
Version: 0.0.2
Summary: Library to asynchronously find and use public proxies from multiple sources.
Home-page: https://github.com/martinzlocha/asyncproxybroker
Author: Martin Zlocha
License: Apache License, Version 2.0
Keywords: proxy finder grabber scraper parser checker broker async asynchronous http https connect asyncio aiohttp
Platform: any
Classifier: Development Status :: 3 - Alpha
Classifier: Intended Audience :: Developers
Classifier: Programming Language :: Python :: 3.7
Classifier: Programming Language :: Python :: 3.8
Classifier: Programming Language :: Python :: 3.9
Classifier: Operating System :: POSIX
Classifier: Operating System :: MacOS :: MacOS X
Classifier: Operating System :: Microsoft :: Windows
Classifier: Topic :: Internet :: WWW/HTTP :: Indexing/Search
Classifier: Topic :: Internet :: Proxy Servers
Classifier: Framework :: AsyncIO
Classifier: License :: OSI Approved :: Apache Software License
Requires-Python: >=3.7
Requires-Dist: aiohttp (>=3.7.3)
Requires-Dist: proxybroker (>=0.3.2)
Requires-Dist: fake-useragent (>=0.1.11)
